preJPProcess.py
preJPProcess-0.0.1.dist-info/LICENSE
preJPProcess-0.0.1.dist-info/METADATA
preJPProcess-0.0.1.dist-info/WHEEL
preJPProcess-0.0.1.dist-info/top_level.txt
preJPProcess-0.0.1.dist-info/RECORD
