Metadata-Version: 2.1
Name: preJPProcess
Version: 0.0.1
Summary: Pre processing the Data Frame
Home-page: https://github.com/jeetbhatt-sys/DataPreProcess
Author: Jeet Bhatt
Author-email: jeetbhatt.va@gmail.com
License: MIT
Platform: UNKNOWN
Classifier: License :: OSI Approved :: MIT License
Classifier: Programming Language :: Python
Classifier: Programming Language :: Python :: 3
Classifier: Programming Language :: Python :: 3.6
Classifier: Programming Language :: Python :: 3.7
License-File: LICENSE
